data_watch/__init__.py
data_watch/api/__init__.py
data_watch/api/model.py
data_watch/api/service/__init__.py
data_watch/api/service/auth/__init__.py
data_watch/api/service/auth/__util.py
data_watch/api/service/auth/asynchronous.py
data_watch/api/service/auth/synchronous.py
data_watch/api/service/group/__init__.py
data_watch/api/service/group/__util.py
data_watch/api/service/group/asynchronous.py
data_watch/api/service/group/model.py
data_watch/api/service/group/synchronous.py
data_watch/api/service/group/view/__init__.py
data_watch/api/service/group/view/__util.py
data_watch/api/service/group/view/asynchronous.py
data_watch/api/service/group/view/model.py
data_watch/api/service/group/view/synchronous.py
data_watch/api/service/job/__init__.py
data_watch/api/service/job/__util.py
data_watch/api/service/job/asynchronous.py
data_watch/api/service/job/model.py
data_watch/api/service/job/synchronous.py
data_watch/api/service/job/view/__init__.py
data_watch/api/service/job/view/__util.py
data_watch/api/service/job/view/asynchronous.py
data_watch/api/service/job/view/model.py
data_watch/api/service/job/view/synchronous.py
data_watch/api/service/rule/__init__.py
data_watch/api/service/rule/__util.py
data_watch/api/service/rule/asynchronous.py
data_watch/api/service/rule/model.py
data_watch/api/service/rule/synchronous.py
data_watch/common/__init__.py
data_watch/common/base.py
data_watch/common/base_enum.py
data_watch/common/config.py
data_watch/common/enum.py
data_watch/common/errors.py
data_watch/common/function.py
data_watch/common/type.py
data_watch/common/date/__init__.py
data_watch/common/date/function.py
data_watch/common/decorators/__init__.py
data_watch/common/decorators/timeit.py
data_watch/common/decorators/authorization/__init__.py
data_watch/common/decorators/authorization/__util.py
data_watch/common/decorators/authorization/asynchronous.py
data_watch/common/decorators/authorization/synchronous.py
data_watch/common/decorators/data/__init__.py
data_watch_sdk-0.0.1b1.dist-info/METADATA
data_watch_sdk-0.0.1b1.dist-info/WHEEL
data_watch_sdk-0.0.1b1.dist-info/top_level.txt
data_watch_sdk-0.0.1b1.dist-info/RECORD
